scaa/__init__.py
scaa/main.py
scaa-0.1.1.dist-info/METADATA
scaa-0.1.1.dist-info/WHEEL
scaa-0.1.1.dist-info/entry_points.txt
scaa-0.1.1.dist-info/RECORD
